pywatchman/__init__.py
pywatchman/bser.c
pywatchman/bser.cpython-311-darwin.so
pywatchman/bser.h
pywatchman/bsermodule.c
pywatchman/capabilities.py
pywatchman/encoding.py
pywatchman/load.py
pywatchman/pybser.py
pywatchman/windows.py
pywatchman-3.0.0.data/scripts/watchman-make
pywatchman-3.0.0.data/scripts/watchman-replicate-subscription
pywatchman-3.0.0.data/scripts/watchman-wait
pywatchman-3.0.0.dist-info/licenses/LICENSE
pywatchman-3.0.0.dist-info/METADATA
pywatchman-3.0.0.dist-info/WHEEL
pywatchman-3.0.0.dist-info/top_level.txt
pywatchman-3.0.0.dist-info/zip-safe
pywatchman-3.0.0.dist-info/RECORD
