Metadata-Version: 2.4
Name: pywatchman
Version: 3.0.0
Summary: Watchman client for Python
Author-email: Meta Source Control Team <sourcecontrol-dev@fb.com>
License: The following license applies to all files within this directory and any
Project-URL: Homepage, https://github.com/facebook/watchman
Project-URL: Issues, https://github.com/facebook/watchman/issues
Keywords: watchman,inotify,fsevents,kevent,kqueue,portfs,filesystem,watcher
Classifier: Development Status :: 5 - Production/Stable
Classifier: Intended Audience :: Developers
Classifier: Topic :: System :: Filesystems
Classifier: License :: OSI Approved :: MIT License
Classifier: Operating System :: OS Independent
Classifier: Programming Language :: Python :: 3
Classifier: Programming Language :: Python :: 3.8
Classifier: Programming Language :: Python :: 3.9
Classifier: Programming Language :: Python :: 3.10
Classifier: Programming Language :: Python :: 3.11
Requires-Python: >=3.8
License-File: LICENSE
Dynamic: license-file
